juno/__init__.py
juno/agent_injection.py
juno/client_setup.py
juno/event_javascript.py
juno/juno.py
juno/magic.py
juno/output_parser.py
juno/prompting_javascript.py
juno/serialize_context.py
juno/version.py
juno/js/juno.min.js
juno_ai-0.0.8.dist-info/METADATA
juno_ai-0.0.8.dist-info/WHEEL
juno_ai-0.0.8.dist-info/top_level.txt
juno_ai-0.0.8.dist-info/RECORD
