Metadata-Version: 2.1
Name: juno-ai
Version: 0.0.8
Home-page: https://github.com/alexi/juno
Author: juno
Author-email: hellojunoai@gmail.com
Classifier: Development Status :: 2 - Pre-Alpha
Classifier: Framework :: IPython
Classifier: Intended Audience :: Developers
Classifier: Intended Audience :: Science/Research
Classifier: Topic :: Multimedia :: Graphics
Classifier: Programming Language :: Python :: 3
Classifier: Programming Language :: Python :: 3.3
Classifier: Programming Language :: Python :: 3.4
Classifier: Programming Language :: Python :: 3.5
Classifier: Programming Language :: Python :: 3.6
Requires-Dist: IPython
Requires-Dist: traitlets
Requires-Dist: notebook (>=5.7.6)
Requires-Dist: validators (>=0.20.0)
